aku_utils/__init__.py
aku_utils/common/__init__.py
aku_utils-0.1.0.dist-info/LICENSE
aku_utils-0.1.0.dist-info/METADATA
aku_utils-0.1.0.dist-info/WHEEL
aku_utils-0.1.0.dist-info/RECORD
