Metadata-Version: 2.3
Name: aku-utils
Version: 0.1.0
Summary: Utils for data processing
License: MIT
Author: stsibikov
Requires-Python: >=3.11
Classifier: License :: OSI Approved :: MIT License
Classifier: Programming Language :: Python :: 3
Classifier: Programming Language :: Python :: 3.11
Classifier: Programming Language :: Python :: 3.12
Classifier: Programming Language :: Python :: 3.13
Requires-Dist: ipykernel (>=6.29.5,<7.0.0)
Requires-Dist: pandas (>=2.2.3,<3.0.0)
